melanin/__init__.py
melanin/__main__.py
melanin-0.1.1.dist-info/LICENSE
melanin-0.1.1.dist-info/METADATA
melanin-0.1.1.dist-info/WHEEL
melanin-0.1.1.dist-info/entry_points.txt
melanin-0.1.1.dist-info/top_level.txt
melanin-0.1.1.dist-info/RECORD
