Metadata-Version: 2.1
Name: melanin
Version: 0.1.1
Summary: Darken Python code exposed to sunlight
Home-page: https://github.com/francois-rozet/melanin
Author: François Rozet
Author-email: francois.rozet@outlook.com
License: MIT License
Keywords: formatter,black,pep8,git
Classifier: Intended Audience :: Developers
Classifier: Intended Audience :: Science/Research
Classifier: License :: OSI Approved :: MIT License
Classifier: Natural Language :: English
Classifier: Operating System :: OS Independent
Classifier: Programming Language :: Python :: 3
Requires-Python: >=3.8
License-File: LICENSE
Requires-Dist: black (>=22.1.0)
Requires-Dist: GitPython (>=3.1.23)
